aws_sso_credential_process/__init__.py
aws_sso_credential_process/aws_configure_sso_profile.py
aws_sso_credential_process/aws_sso_credential_process.py
aws_sso_credential_process/credentials.py
aws_sso_credential_process/exceptions.py
aws_sso_credential_process/interactive.py
aws_sso_credential_process/utils.py
aws_sso_credential_process-0.3.1.dist-info/entry_points.txt
aws_sso_credential_process-0.3.1.dist-info/LICENSE
aws_sso_credential_process-0.3.1.dist-info/WHEEL
aws_sso_credential_process-0.3.1.dist-info/METADATA
aws_sso_credential_process-0.3.1.dist-info/RECORD
